{
 "name": "flare",
 "children": [
  {
    "name": "Telnor", 
    "size": 1000,
    "type":"root",
    "children":[
      {"name":"Oscar","size":8,"type":"leaf"},
      {"name":"Vineet","size":17,"type":"leaf"},
      {"name":"Farhad","size":21,"type":"leaf"}
    ]
  },
  {
    "name": "SuperMarket", 
    "size": 1000,
    "type":"root",
    "children":[
      {"name":"Liccy","size":32,"type":"leaf"},
      {"name":"Daniel","size":32,"type":"leaf"},
      {"name":"Chris","size":32,"type":"leaf"},
      {"name":"Jeremy","size":32,"type":"leaf"}
    ]
  },
  {
    "name": "Bankster", 
    "size": 1000,
    "type":"root",
    "children":[
      {"name":"Liccy","size":32,"type":"leaf"},
      {"name":"Daniel","size":32,"type":"leaf"},
      {"name":"Chris","size":32,"type":"leaf"},
      {"name":"Jeremy","size":32,"type":"leaf"},
      {"name":"Liccy","size":32,"type":"leaf"},
      {"name":"Daniel","size":32,"type":"leaf"},
      {"name":"Chris","size":32,"type":"leaf"},
      {"name":"Jeremy","size":32,"type":"leaf"},
      {"name":"Liccy","size":32,"type":"leaf"},
      {"name":"Daniel","size":32,"type":"leaf"},
      {"name":"Chris","size":32,"type":"leaf"},
      {"name":"Jeremy","size":32,"type":"leaf"},
      {"name":"Liccy","size":32,"type":"leaf"},
      {"name":"Daniel","size":32,"type":"leaf"},
      {"name":"Chris","size":32,"type":"leaf"},
      {"name":"Jeremy","size":32,"type":"leaf"},
      {"name":"Liccy","size":32,"type":"leaf"},
      {"name":"Daniel","size":32,"type":"leaf"},
      {"name":"Chris","size":32,"type":"leaf"},
      {"name":"Jeremy","size":32,"type":"leaf"},
      {"name":"Liccy","size":32,"type":"leaf"},
      {"name":"Daniel","size":32,"type":"leaf"},
      {"name":"Chris","size":32,"type":"leaf"},
      {"name":"Jeremy","size":32,"type":"leaf"},
      {"name":"Liccy","size":32,"type":"leaf"},
      {"name":"Daniel","size":32,"type":"leaf"},
      {"name":"Chris","size":32,"type":"leaf"},
      {"name":"Jeremy","size":32,"type":"leaf"},
      {"name":"Liccy","size":32,"type":"leaf"},
      {"name":"Daniel","size":32,"type":"leaf"},
      {"name":"Chris","size":32,"type":"leaf"},
      {"name":"Jeremy","size":32,"type":"leaf"}
    ]
  }
 ]
}